Runningprojectmodule/APIcall_v2.py
Runningprojectmodule/__init__.py
Runningprojectmodule/config.py
Runningprojectmodule/data_extraction.py
Runningprojectmodule/dataset.py
Runningprojectmodule/features.py
Runningprojectmodule/plots.py
Runningprojectmodule/project_instance.py
Runningprojectmodule/modeling/__init__.py
Runningprojectmodule/modeling/predict.py
Runningprojectmodule/modeling/train.py
runningprojectmodule-0.0.1.dist-info/licenses/LICENSE
runningprojectmodule-0.0.1.dist-info/WHEEL
runningprojectmodule-0.0.1.dist-info/METADATA
runningprojectmodule-0.0.1.dist-info/RECORD
