Metadata-Version: 2.4
Name: Runningprojectmodule
Version: 0.0.1
Summary: Project predicting injury rates in runners based on information about training volume
Author: Milo
Requires-Python: ~=3.10.0
Classifier: Programming Language :: Python :: 3
Classifier: License :: OSI Approved :: MIT License
License-File: LICENSE
Requires-Dist: black
Requires-Dist: flake8
Requires-Dist: isort
Requires-Dist: loguru
Requires-Dist: mkdocs
Requires-Dist: pip
Requires-Dist: pytest
Requires-Dist: python-dotenv
Requires-Dist: tqdm
Requires-Dist: typer
Requires-Dist: xgboost
Requires-Dist: hyperopt
Requires-Dist: bayesian_optimization==1.4.0
Requires-Dist: colorama==0.4.4
